setup.py
invoicing/__init__.py
invoicing/invoice.py
xlsx_to_pdf.egg-info/PKG-INFO
xlsx_to_pdf.egg-info/SOURCES.txt
xlsx_to_pdf.egg-info/dependency_links.txt
xlsx_to_pdf.egg-info/requires.txt
xlsx_to_pdf.egg-info/top_level.txt